data/__init__.py
data/checking.py
data/config.py
database/__init__.py
database/db_utils.py
database/functions.py
database/models.py
filters/__init__.py
filters/admin_filter.py
filters/channel_filter.py
filters/group_filter.py
filters/user_filter.py
handlers/__init__.py
handlers/admin/__init__.py
handlers/admin/admin.py
handlers/channel/__init__.py
handlers/channel/channel.py
handlers/group/__init__.py
handlers/group/group.py
handlers/users/__init__.py
handlers/users/users.py
keyboards/__init__.py
keyboards/inline.py
keyboards/reply.py
states/__init__.py
states/example_state.py
utils/__init__.py
utils/misc.py
utils/notify_admins.py
utils/set_bot_commands.py
aiogram_template-1.dist-info/METADATA
aiogram_template-1.dist-info/WHEEL
aiogram_template-1.dist-info/top_level.txt
aiogram_template-1.dist-info/RECORD
