Metadata-Version: 2.1
Name: aiogram_template
Version: 1
Summary: Aiogram3 kutubxonasi uchun template
Home-page: https://github.com/rafkix/Aiogram-3-TEmplate
Author: Rafkix
Author-email: rafkixuz@gmail.com
Classifier: Programming Language :: Python :: 3
Classifier: License :: OSI Approved :: MIT License
Classifier: Operating System :: OS Independent
Requires-Dist: aiogram
Requires-Dist: environs
